Workbook

Sheet Pre-Bid Queries
A1: PRE-BID QUERIES – PROCUREMENT OF GPU SERVERS FOR ICT DTE NUST H-12 CAMPUS ISLAMABAD (Tender Ref: P158775)
A2: Submitted by: Premier Systems (Pvt) Ltd | Procuring Agency: NUST (P&LP), P&LP Dte, NUST H-12 | Pre-bid meeting: Mon 26 Oct 2026, 02:30 PM | Clarification deadline (EPADS): Mon 2 Nov 2026 | Bid submission: Thu 5 Nov 2026, 11:00 AM
A3: Legend: yellow columns = RFP page and clause reference; green column = to be filled by NUST. Page numbers follow the RFP footer 'Page X of 85' (PDF viewer page = printed page + 2).
A5: S. No | B5: Section | C5: RFP Page No. (as printed) | D5: Clause / Reference | E5: RFP Provision (as stated) | F5: Query / Clarification Sought | G5: Category | H5: Priority | I5: NUST Response
A6: 14 | B6: Evaluation | C6: 32-33 | D6: Evaluation Criteria – Accelerator vendor partnership (5 marks) | E6: NVIDIA Partner Network or equivalent: Elite (5), Preferred (3), Registered/member (1). | F6: Please confirm whether the bidder's own NPN status is required, or whether the server OEM's or distributor's NVIDIA status may be considered. Is a specific NPN competency (e.g. Compute / AI infrastructure) required? | G6: Evaluation | H6: Medium
A7: 23 | B7: Schedule | C7: 37, 40, 46 | D7: Items/Lots; Option-1 Ser 3; Option-2 Ser 3 | E7: Data-centre GPUs (RTX PRO 6000 Blackwell Server Edition / H200 NVL) to be new, genuine and supplied via OEM channel. | F7: Data-centre GPUs are subject to US export regulations and long OEM lead times. Will NUST provide an End-User / End-Use Certificate when required by the OEM? Please confirm that delays caused by export-licence processing beyond the bidder's control will be treated as excusable delay (no liquidated damages), and consider a delivery period of 90-120 days. | G7: Schedule | H7: High
A8: 24 | B8: Schedule | C8: 37, 43, 50 | D8: Items/Lots – Delivery address; Section-2 Ser 1 | E8: Delivery address: P&LP Dte, Near NUST MT Area. Installation: 'existing data centre'. | F8: Please confirm the installation site (ICT Dte data centre location) and whether goods are to be delivered directly to the data centre rather than to P&LP Dte. | G8: Schedule | H8: Low
A9: 25 | B9: Commercial | C9: 27, 30, 64 | D9: BDS 9 (ITB 16.1); Eligibility Criteria Row 4; GCC 36 | E9: Prices in PKR; payment after deduction of income tax and part of sales tax; supplier responsible for taxes until delivery. | F9: Please confirm that quoted prices shall be inclusive of all applicable taxes (GST on goods and ICT/provincial sales tax on services) and the withholding rates NUST will apply. Should taxes be shown separately in the price schedule? | G9: Commercial | H9: High
A10: 26 | B10: Commercial | C10: 52 | D10: Price Schedule | E10: One line per item (Unit Price / Total Price). Spec (Section 1 Ser 6) requires bidders to itemize each chargeable subscription. | F10: May bidders attach a detailed itemized BOQ (hardware, software subscriptions, services) with the financial bid, with the EPADS price schedule carrying the total per option? Which prevails in case of discrepancy? | G10: Commercial | H10: Medium
A11: 27 | B11: Commercial | C11: 11, 27 | D11: ITB 15.6; BDS 8 | E11: Prices fixed; adjustable price bids rejected. | F11: Given that hardware and subscriptions are USD-denominated and imported, will NUST consider an exchange-rate variation clause if PKR/USD moves beyond a set band (e.g. ±3%) between bid submission and LC/payment? | G11: Commercial | H11: Medium
A12: 28 | B12: Commercial | C12: 63, 68 | D12: GCC 32; SCC (GC Clause 32) | E12: Payment 'according to the actual invoice or running bills ... within the time given in the conditions of the contract'. No milestones or payment period stated. | F12: Please specify payment milestones and the payment period. We propose: 70% on delivery and inspection, 30% on installation, commissioning and acceptance, payable within 30 days of invoice. Is advance payment against a bank guarantee possible? | G12: Commercial | H12: High
A13: 29 | B13: Commercial | C13: 61-62, 68 | D13: GCC 23; SCC (GC Clause 23) | E13: Performance guarantee 5% of contract price as Pay Order; discharged 30 days after completion of performance obligations including warranty (GCC 23.5). | F13: (a) Is a bank guarantee acceptable instead of a Pay Order? (b) Since GCC 23.5 links release to warranty completion, the 5% would be held for 3 years. Please confirm release on acceptance, or allow conversion to a warranty bank guarantee. (c) GCC 23.6 states the bid security shall not be substituted with the Performance Guarantee; please confirm when the successful bidder's bid security will be returned (ITB 18.8). | G13: Commercial | H13: Medium
A14: 35 | B14: Technical – Site | C14: 39, 43, 45 | D14: Option-1 Ser 1; Option-2 Ser 1; Section-2 Ser 1 | E14: Racking into existing hot/cold-aisle data centre; blanking panels to be provided. | F14: Please share: rack make/model and usable depth (mm), available rack units, power available per rack (kW), PDU make and outlet type (C13/C19), and whether A/B feeds are on separate UPS. A 4 x 600 W GPU server can draw roughly 3.5-4.5 kW; please confirm the rack can support this. | G14: Technical | H14: High
A15: 36 | B15: Technical – Site | C15: 45 | D15: Option-2 Ser 1 (also relevant to Option-1) | E15: Bidder to state OEM-supported maximum inlet (cold-aisle) temperature. | F15: Please share the current cold-aisle supply temperature and humidity in NUST's data centre so that the offered configuration can be validated by the OEM for continuous full-TDP operation. | G15: Technical | H15: Medium
A16: 37 | B16: Technical – Site | C16: 41, 47 | D16: Option-1 Ser 8; Option-2 Ser 8 (Power supplies) | E16: Minimum N+1 PSU redundancy at full load; design shall support independent A and B feeds. | F16: N+1 and A/B feed redundancy are different requirements. With A/B feeds, losing one feed removes half the PSUs, which requires N+N (grid) redundancy. Please confirm whether N+1 is sufficient, or whether full-load operation on a single feed (N+N) is required. | G16: Technical | H16: High
A17: 38 | B17: Technical – Hardware | C17: 39, 45 | D17: Option-1 Ser 1; Option-2 Ser 1 | E17: Dual Intel Xeon 6 or 5th Gen Xeon Scalable, minimum 48 physical cores each. | F17: Will AMD EPYC 9004/9005 processors with equal or higher core count be accepted as equivalent? Many OEM-certified GPU platforms are offered on both, and allowing either would increase competition. | G17: Technical | H17: Medium
... A32: 55 | B32: Services | C32: 44, 50 | D32: Section-2 Ser 6 (Training and certification) | E32: Onsite/virtual knowledge transfer; training material and certificates to be provided. | F32: Please specify the number of participants and training days. Please confirm 'certificates' means training completion certificates issued by the bidder/OEM, not vendor certification exam vouchers (e.g. NVIDIA, Red Hat). | G32: Services | H32: Medium

Sheet Summary
A1: Query Summary
A3: Category | B3: Total | C3: High | D3: Medium | E3: Low
A4: Bid Security | B4: =COUNTIF('Pre-Bid Queries'!$G$6:$G$32,A4) -> 0 | C4: =COUNTIFS('Pre-Bid Queries'!$G$6:$G$32,$A4,'Pre-Bid Queries'!$H$6:$H$32,"High") -> 0 | D4: =COUNTIFS('Pre-Bid Queries'!$G$6:$G$32,$A4,'Pre-Bid Queries'!$H$6:$H$32,"Medium") -> 0 | E4: =COUNTIFS('Pre-Bid Queries'!$G$6:$G$32,$A4,'Pre-Bid Queries'!$H$6:$H$32,"Low") -> 0
A5: Submission | B5: =COUNTIF('Pre-Bid Queries'!$G$6:$G$32,A5) -> 0 | C5: =COUNTIFS('Pre-Bid Queries'!$G$6:$G$32,$A5,'Pre-Bid Queries'!$H$6:$H$32,"High") -> 0 | D5: =COUNTIFS('Pre-Bid Queries'!$G$6:$G$32,$A5,'Pre-Bid Queries'!$H$6:$H$32,"Medium") -> 0 | E5: =COUNTIFS('Pre-Bid Queries'!$G$6:$G$32,$A5,'Pre-Bid Queries'!$H$6:$H$32,"Low") -> 0
A6: Evaluation | B6: =COUNTIF('Pre-Bid Queries'!$G$6:$G$32,A6) -> 1 | C6: =COUNTIFS('Pre-Bid Queries'!$G$6:$G$32,$A6,'Pre-Bid Queries'!$H$6:$H$32,"High") -> 0 | D6: =COUNTIFS('Pre-Bid Queries'!$G$6:$G$32,$A6,'Pre-Bid Queries'!$H$6:$H$32,"Medium") -> 1 | E6: =COUNTIFS('Pre-Bid Queries'!$G$6:$G$32,$A6,'Pre-Bid Queries'!$H$6:$H$32,"Low") -> 0
A7: Schedule | B7: =COUNTIF('Pre-Bid Queries'!$G$6:$G$32,A7) -> 2 | C7: =COUNTIFS('Pre-Bid Queries'!$G$6:$G$32,$A7,'Pre-Bid Queries'!$H$6:$H$32,"High") -> 1 | D7: =COUNTIFS('Pre-Bid Queries'!$G$6:$G$32,$A7,'Pre-Bid Queries'!$H$6:$H$32,"Medium") -> 0 | E7: =COUNTIFS('Pre-Bid Queries'!$G$6:$G$32,$A7,'Pre-Bid Queries'!$H$6:$H$32,"Low") -> 1
A8: Commercial | B8: =COUNTIF('Pre-Bid Queries'!$G$6:$G$32,A8) -> 5 | C8: =COUNTIFS('Pre-Bid Queries'!$G$6:$G$32,$A8,'Pre-Bid Queries'!$H$6:$H$32,"High") -> 2 | D8: =COUNTIFS('Pre-Bid Queries'!$G$6:$G$32,$A8,'Pre-Bid Queries'!$H$6:$H$32,"Medium") -> 3 | E8: =COUNTIFS('Pre-Bid Queries'!$G$6:$G$32,$A8,'Pre-Bid Queries'!$H$6:$H$32,"Low") -> 0
A9: Contractual | B9: =COUNTIF('Pre-Bid Queries'!$G$6:$G$32,A9) -> 0 | C9: =COUNTIFS('Pre-Bid Queries'!$G$6:$G$32,$A9,'Pre-Bid Queries'!$H$6:$H$32,"High") -> 0 | D9: =COUNTIFS('Pre-Bid Queries'!$G$6:$G$32,$A9,'Pre-Bid Queries'!$H$6:$H$32,"Medium") -> 0 | E9: =COUNTIFS('Pre-Bid Queries'!$G$6:$G$32,$A9,'Pre-Bid Queries'!$H$6:$H$32,"Low") -> 0
A10: Technical | B10: =COUNTIF('Pre-Bid Queries'!$G$6:$G$32,A10) -> 15 | C10: =COUNTIFS('Pre-Bid Queries'!$G$6:$G$32,$A10,'Pre-Bid Queries'!$H$6:$H$32,"High") -> 5 | D10: =COUNTIFS('Pre-Bid Queries'!$G$6:$G$32,$A10,'Pre-Bid Queries'!$H$6:$H$32,"Medium") -> 10 | E10: =COUNTIFS('Pre-Bid Queries'!$G$6:$G$32,$A10,'Pre-Bid Queries'!$H$6:$H$32,"Low") -> 0
A11: Services | B11: =COUNTIF('Pre-Bid Queries'!$G$6:$G$32,A11) -> 4 | C11: =COUNTIFS('Pre-Bid Queries'!$G$6:$G$32,$A11,'Pre-Bid Queries'!$H$6:$H$32,"High") -> 2 | D11: =COUNTIFS('Pre-Bid Queries'!$G$6:$G$32,$A11,'Pre-Bid Queries'!$H$6:$H$32,"Medium") -> 2 | E11: =COUNTIFS('Pre-Bid Queries'!$G$6:$G$32,$A11,'Pre-Bid Queries'!$H$6:$H$32,"Low") -> 0
A12: Total | B12: =SUM(B4:B11) -> 27 | C12: =SUM(C4:C11) -> 10 | D12: =SUM(D4:D11) -> 16 | E12: =SUM(E4:E11) -> 1
A13: Answered by NUST | B13: =COUNTA('Pre-Bid Queries'!$I$6:$I$32) -> 0
